{
  "a_comp_cor_00": {
    "CumulativeVarianceExplained": 0.0179906683,
    "Mask": "combined",
    "Method": "aCompCor",
    "Retained": true,
    "SingularValue": 68.0210118479,
    "VarianceExplained": 0.0179906683
  },
  "a_comp_cor_01": {
    "CumulativeVarianceExplained": 0.0349118889,
    "Mask": "combined",
    "Method": "aCompCor",
    "Retained": true,
    "SingularValue": 65.9682987618,
    "VarianceExplained": 0.0169212206
  },
  "a_comp_cor_02": {
    "CumulativeVarianceExplained": 0.0494105851,
    "Mask": "combined",
    "Method": "aCompCor",
    "Retained": true,
    "SingularValue": 61.0638124953,
    "VarianceExplained": 0.0144986962
  },
  "a_comp_cor_03": {
    "CumulativeVarianceExplained": 0.0622357451,
    "Mask": "combined",
    "Method": "aCompCor",
    "Retained": true,
    "SingularValue": 57.4315895316,
    "VarianceExplained": 0.01282516
  },
  "a_comp_cor_04": {
    "CumulativeVarianceExplained": 0.0741163016,
    "Mask": "combined",
    "Method": "aCompCor",
    "Retained": true,
    "SingularValue": 55.2761557004,
    "VarianceExplained": 0.0118805565
  },
  "a_comp_cor_05": {
    "CumulativeVarianceExplained": 0.0849515248,
    "Mask": "combined",
    "Method": "aCompCor",
    "Retained": true,
    "SingularValue": 52.7883845887,
    "VarianceExplained": 0.0108352232
  },
  "a_comp_cor_06": {
    "CumulativeVarianceExplained": 0.0951226367,
    "Mask": "combined",
    "Method": "aCompCor",
    "Retained": true,
    "SingularValue": 51.1450556268,
    "VarianceExplained": 0.0101711118
  },
  "a_comp_cor_07": {
    "CumulativeVarianceExplained": 0.1050865015,
    "Mask": "combined",
    "Method": "aCompCor",
    "Retained": true,
    "SingularValue": 50.6213069763,
    "VarianceExplained": 0.0099638648
  },
  "a_comp_cor_08": {
    "CumulativeVarianceExplained": 0.1149506031,
    "Mask": "combined",
    "Method": "aCompCor",
    "Retained": true,
    "SingularValue": 50.3672463818,
    "VarianceExplained": 0.0098641016
  },
  "a_comp_cor_09": {
    "CumulativeVarianceExplained": 0.1246393719,
    "Mask": "combined",
    "Method": "aCompCor",
    "Retained": true,
    "SingularValue": 49.9176046209,
    "VarianceExplained": 0.0096887688
  },
  "a_comp_cor_10": {
    "CumulativeVarianceExplained": 0.1343145441,
    "Mask": "combined",
    "Method": "aCompCor",
    "Retained": true,
    "SingularValue": 49.8825667875,
    "VarianceExplained": 0.0096751722
  },
  "a_comp_cor_11": {
    "CumulativeVarianceExplained": 0.1438600063,
    "Mask": "combined",
    "Method": "aCompCor",
    "Retained": true,
    "SingularValue": 49.5470635614,
    "VarianceExplained": 0.0095454622
  },
  "a_comp_cor_12": {
    "CumulativeVarianceExplained": 0.1533050677,
    "Mask": "combined",
    "Method": "aCompCor",
    "Retained": true,
    "SingularValue": 49.2858026676,
    "VarianceExplained": 0.0094450614
  },
  "a_comp_cor_13": {
    "CumulativeVarianceExplained": 0.1626554273,
    "Mask": "combined",
    "Method": "aCompCor",
    "Retained": true,
    "SingularValue": 49.0380956825,
    "VarianceExplained": 0.0093503596
  },
  "a_comp_cor_14": {
    "CumulativeVarianceExplained": 0.1719622309,
    "Mask": "combined",
    "Method": "aCompCor",
    "Retained": true,
    "SingularValue": 48.9237472827,
    "VarianceExplained": 0.0093068036
  },
  "a_comp_cor_15": {
    "CumulativeVarianceExplained": 0.1811656215,
    "Mask": "combined",
    "Method": "aCompCor",
    "Retained": true,
    "SingularValue": 48.6511788272,
    "VarianceExplained": 0.0092033906
  },
  "a_comp_cor_16": {
    "CumulativeVarianceExplained": 0.1902287011,
    "Mask": "combined",
    "Method": "aCompCor",
    "Retained": true,
    "SingularValue": 48.278896744,
    "VarianceExplained": 0.0090630796
  },
  "a_comp_cor_17": {
    "CumulativeVarianceExplained": 0.1991576855,
    "Mask": "combined",
    "Method": "aCompCor",
    "Retained": true,
    "SingularValue": 47.9204042384,
    "VarianceExplained": 0.0089289844
  },
  "a_comp_cor_18": {
    "CumulativeVarianceExplained": 0.2079312151,
    "Mask": "combined",
    "Method": "aCompCor",
    "Retained": true,
    "SingularValue": 47.5014222434,
    "VarianceExplained": 0.0087735296
  },
  "a_comp_cor_19": {
    "CumulativeVarianceExplained": 0.2166726325,
    "Mask": "combined",
    "Method": "aCompCor",
    "Retained": true,
    "SingularValue": 47.4144122264,
    "VarianceExplained": 0.0087414175
  },
  "a_comp_cor_20": {
    "CumulativeVarianceExplained": 0.2252794982,
    "Mask": "combined",
    "Method": "aCompCor",
    "Retained": true,
    "SingularValue": 47.0480851242,
    "VarianceExplained": 0.0086068656
  },
  "a_comp_cor_21": {
    "CumulativeVarianceExplained": 0.2338515689,
    "Mask": "combined",
    "Method": "aCompCor",
    "Retained": true,
    "SingularValue": 46.9528881374,
    "VarianceExplained": 0.0085720707
  },
  "a_comp_cor_22": {
    "CumulativeVarianceExplained": 0.2423479677,
    "Mask": "combined",
    "Method": "aCompCor",
    "Retained": true,
    "SingularValue": 46.7451853042,
    "VarianceExplained": 0.0084963988
  },
  "a_comp_cor_23": {
    "CumulativeVarianceExplained": 0.2508098093,
    "Mask": "combined",
    "Method": "aCompCor",
    "Retained": true,
    "SingularValue": 46.6500256319,
    "VarianceExplained": 0.0084618416
  },
  "a_comp_cor_24": {
    "CumulativeVarianceExplained": 0.259157295,
    "Mask": "combined",
    "Method": "aCompCor",
    "Retained": true,
    "SingularValue": 46.3337319793,
    "VarianceExplained": 0.0083474857
  },
  "a_comp_cor_25": {
    "CumulativeVarianceExplained": 0.2674383591,
    "Mask": "combined",
    "Method": "aCompCor",
    "Retained": true,
    "SingularValue": 46.1490230832,
    "VarianceExplained": 0.008281064
  },
  "a_comp_cor_26": {
    "CumulativeVarianceExplained": 0.2756378284,
    "Mask": "combined",
    "Method": "aCompCor",
    "Retained": true,
    "SingularValue": 45.9211032705,
    "VarianceExplained": 0.0081994693
  },
  "a_comp_cor_27": {
    "CumulativeVarianceExplained": 0.2837559065,
    "Mask": "combined",
    "Method": "aCompCor",
    "Retained": true,
    "SingularValue": 45.6926191518,
    "VarianceExplained": 0.0081180781
  },
  "a_comp_cor_28": {
    "CumulativeVarianceExplained": 0.291856511,
    "Mask": "combined",
    "Method": "aCompCor",
    "Retained": true,
    "SingularValue": 45.643417542,
    "VarianceExplained": 0.0081006045
  },
  "a_comp_cor_29": {
    "CumulativeVarianceExplained": 0.2998781354,
    "Mask": "combined",
    "Method": "aCompCor",
    "Retained": true,
    "SingularValue": 45.4203629911,
    "VarianceExplained": 0.0080216244
  },
  "a_comp_cor_30": {
    "CumulativeVarianceExplained": 0.3078426366,
    "Mask": "combined",
    "Method": "aCompCor",
    "Retained": true,
    "SingularValue": 45.258351595,
    "VarianceExplained": 0.0079645012
  },
  "a_comp_cor_31": {
    "CumulativeVarianceExplained": 0.3157270424,
    "Mask": "combined",
    "Method": "aCompCor",
    "Retained": true,
    "SingularValue": 45.0302051893,
    "VarianceExplained": 0.0078844058
  },
  "a_comp_cor_32": {
    "CumulativeVarianceExplained": 0.3235364059,
    "Mask": "combined",
    "Method": "aCompCor",
    "Retained": true,
    "SingularValue": 44.8153981871,
    "VarianceExplained": 0.0078093635
  },
  "a_comp_cor_33": {
    "CumulativeVarianceExplained": 0.3312857986,
    "Mask": "combined",
    "Method": "aCompCor",
    "Retained": true,
    "SingularValue": 44.6429899638,
    "VarianceExplained": 0.0077493927
  },
  "a_comp_cor_34": {
    "CumulativeVarianceExplained": 0.3389745438,
    "Mask": "combined",
    "Method": "aCompCor",
    "Retained": true,
    "SingularValue": 44.467956828,
    "VarianceExplained": 0.0076887452
  },
  "a_comp_cor_35": {
    "CumulativeVarianceExplained": 0.3465462804,
    "Mask": "combined",
    "Method": "aCompCor",
    "Retained": true,
    "SingularValue": 44.1282990285,
    "VarianceExplained": 0.0075717365
  },
  "a_comp_cor_36": {
    "CumulativeVarianceExplained": 0.3540637447,
    "Mask": "combined",
    "Method": "aCompCor",
    "Retained": true,
    "SingularValue": 43.9698647186,
    "VarianceExplained": 0.0075174644
  },
  "a_comp_cor_37": {
    "CumulativeVarianceExplained": 0.3615097549,
    "Mask": "combined",
    "Method": "aCompCor",
    "Retained": true,
    "SingularValue": 43.7603969483,
    "VarianceExplained": 0.0074460102
  },
  "a_comp_cor_38": {
    "CumulativeVarianceExplained": 0.3689294033,
    "Mask": "combined",
    "Method": "aCompCor",
    "Retained": true,
    "SingularValue": 43.6828638185,
    "VarianceExplained": 0.0074196484
  },
  "a_comp_cor_39": {
    "CumulativeVarianceExplained": 0.3762790648,
    "Mask": "combined",
    "Method": "aCompCor",
    "Retained": true,
    "SingularValue": 43.4763532327,
    "VarianceExplained": 0.0073496615
  },
  "a_comp_cor_40": {
    "CumulativeVarianceExplained": 0.3835826046,
    "Mask": "combined",
    "Method": "aCompCor",
    "Retained": true,
    "SingularValue": 43.3397241504,
    "VarianceExplained": 0.0073035399
  },
  "a_comp_cor_41": {
    "CumulativeVarianceExplained": 0.3908805854,
    "Mask": "combined",
    "Method": "aCompCor",
    "Retained": true,
    "SingularValue": 43.3232269204,
    "VarianceExplained": 0.0072979808
  },
  "a_comp_cor_42": {
    "CumulativeVarianceExplained": 0.3980972872,
    "Mask": "combined",
    "Method": "aCompCor",
    "Retained": true,
    "SingularValue": 43.0813019004,
    "VarianceExplained": 0.0072167018
  },
  "a_comp_cor_43": {
    "CumulativeVarianceExplained": 0.4052658536,
    "Mask": "combined",
    "Method": "aCompCor",
    "Retained": true,
    "SingularValue": 42.9373857515,
    "VarianceExplained": 0.0071685665
  },
  "a_comp_cor_44": {
    "CumulativeVarianceExplained": 0.4123670712,
    "Mask": "combined",
    "Method": "aCompCor",
    "Retained": true,
    "SingularValue": 42.7352108411,
    "VarianceExplained": 0.0071012176
  },
  "a_comp_cor_45": {
    "CumulativeVarianceExplained": 0.4194192611,
    "Mask": "combined",
    "Method": "aCompCor",
    "Retained": true,
    "SingularValue": 42.5874306378,
    "VarianceExplained": 0.0070521899
  },
  "a_comp_cor_46": {
    "CumulativeVarianceExplained": 0.4264213373,
    "Mask": "combined",
    "Method": "aCompCor",
    "Retained": true,
    "SingularValue": 42.4358451537,
    "VarianceExplained": 0.0070020762
  },
  "a_comp_cor_47": {
    "CumulativeVarianceExplained": 0.4334096266,
    "Mask": "combined",
    "Method": "aCompCor",
    "Retained": true,
    "SingularValue": 42.3940470567,
    "VarianceExplained": 0.0069882893
  },
  "a_comp_cor_48": {
    "CumulativeVarianceExplained": 0.4403491014,
    "Mask": "combined",
    "Method": "aCompCor",
    "Retained": true,
    "SingularValue": 42.2457226015,
    "VarianceExplained": 0.0069394748
  },
  "a_comp_cor_49": {
    "CumulativeVarianceExplained": 0.4472621189,
    "Mask": "combined",
    "Method": "aCompCor",
    "Retained": true,
    "SingularValue": 42.1651129209,
    "VarianceExplained": 0.0069130175
  },
  "a_comp_cor_50": {
    "CumulativeVarianceExplained": 0.4541111581,
    "Mask": "combined",
    "Method": "aCompCor",
    "Retained": true,
    "SingularValue": 41.9695456158,
    "VarianceExplained": 0.0068490392
  },
  "a_comp_cor_51": {
    "CumulativeVarianceExplained": 0.4609000785,
    "Mask": "combined",
    "Method": "aCompCor",
    "Retained": true,
    "SingularValue": 41.7849415477,
    "VarianceExplained": 0.0067889204
  },
  "a_comp_cor_52": {
    "CumulativeVarianceExplained": 0.4676063184,
    "Mask": "combined",
    "Method": "aCompCor",
    "Retained": true,
    "SingularValue": 41.5297180098,
    "VarianceExplained": 0.0067062399
  },
  "a_comp_cor_53": {
    "CumulativeVarianceExplained": 0.4742938723,
    "Mask": "combined",
    "Method": "aCompCor",
    "Retained": true,
    "SingularValue": 41.4718194216,
    "VarianceExplained": 0.0066875539
  },
  "a_comp_cor_54": {
    "CumulativeVarianceExplained": 0.480971141,
    "Mask": "combined",
    "Method": "aCompCor",
    "Retained": true,
    "SingularValue": 41.4399160221,
    "VarianceExplained": 0.0066772687
  },
  "a_comp_cor_55": {
    "CumulativeVarianceExplained": 0.4875962011,
    "Mask": "combined",
    "Method": "aCompCor",
    "Retained": true,
    "SingularValue": 41.2775916281,
    "VarianceExplained": 0.0066250601
  },
  "a_comp_cor_56": {
    "CumulativeVarianceExplained": 0.4941418705,
    "Mask": "combined",
    "Method": "aCompCor",
    "Retained": true,
    "SingularValue": 41.0295235412,
    "VarianceExplained": 0.0065456694
  },
  "a_comp_cor_57": {
    "CumulativeVarianceExplained": 0.5006416559,
    "Mask": "combined",
    "Method": "aCompCor",
    "Retained": true,
    "SingularValue": 40.8854656195,
    "VarianceExplained": 0.0064997854
  },
  "c_comp_cor_00": {
    "CumulativeVarianceExplained": 0.1083932151,
    "Mask": "CSF",
    "Method": "aCompCor",
    "Retained": true,
    "SingularValue": 58.1090822191,
    "VarianceExplained": 0.1083932151
  },
  "c_comp_cor_01": {
    "CumulativeVarianceExplained": 0.1750183662,
    "Mask": "CSF",
    "Method": "aCompCor",
    "Retained": true,
    "SingularValue": 45.5577293846,
    "VarianceExplained": 0.0666251511
  },
  "c_comp_cor_02": {
    "CumulativeVarianceExplained": 0.2269399366,
    "Mask": "CSF",
    "Method": "aCompCor",
    "Retained": true,
    "SingularValue": 40.2176672685,
    "VarianceExplained": 0.0519215704
  },
  "c_comp_cor_03": {
    "CumulativeVarianceExplained": 0.273679668,
    "Mask": "CSF",
    "Method": "aCompCor",
    "Retained": true,
    "SingularValue": 38.1580412926,
    "VarianceExplained": 0.0467397315
  },
  "c_comp_cor_04": {
    "CumulativeVarianceExplained": 0.3120978098,
    "Mask": "CSF",
    "Method": "aCompCor",
    "Retained": true,
    "SingularValue": 34.5948255305,
    "VarianceExplained": 0.0384181418
  },
  "c_comp_cor_05": {
    "CumulativeVarianceExplained": 0.3464608287,
    "Mask": "CSF",
    "Method": "aCompCor",
    "Retained": true,
    "SingularValue": 32.7181411987,
    "VarianceExplained": 0.0343630189
  },
  "c_comp_cor_06": {
    "CumulativeVarianceExplained": 0.3730895405,
    "Mask": "CSF",
    "Method": "aCompCor",
    "Retained": true,
    "SingularValue": 28.8016949215,
    "VarianceExplained": 0.0266287118
  },
  "c_comp_cor_07": {
    "CumulativeVarianceExplained": 0.3988311112,
    "Mask": "CSF",
    "Method": "aCompCor",
    "Retained": true,
    "SingularValue": 28.3178637993,
    "VarianceExplained": 0.0257415707
  },
  "c_comp_cor_08": {
    "CumulativeVarianceExplained": 0.4212420629,
    "Mask": "CSF",
    "Method": "aCompCor",
    "Retained": true,
    "SingularValue": 26.4224519615,
    "VarianceExplained": 0.0224109517
  },
  "c_comp_cor_09": {
    "CumulativeVarianceExplained": 0.4403988043,
    "Mask": "CSF",
    "Method": "aCompCor",
    "Retained": true,
    "SingularValue": 24.4288928837,
    "VarianceExplained": 0.0191567414
  },
  "c_comp_cor_10": {
    "CumulativeVarianceExplained": 0.4580739739,
    "Mask": "CSF",
    "Method": "aCompCor",
    "Retained": true,
    "SingularValue": 23.4652271306,
    "VarianceExplained": 0.0176751696
  },
  "c_comp_cor_11": {
    "CumulativeVarianceExplained": 0.4750569992,
    "Mask": "CSF",
    "Method": "aCompCor",
    "Retained": true,
    "SingularValue": 23.0012000457,
    "VarianceExplained": 0.0169830253
  },
  "c_comp_cor_12": {
    "CumulativeVarianceExplained": 0.4914071086,
    "Mask": "CSF",
    "Method": "aCompCor",
    "Retained": true,
    "SingularValue": 22.568531345,
    "VarianceExplained": 0.0163501094
  },
  "c_comp_cor_13": {
    "CumulativeVarianceExplained": 0.5075920863,
    "Mask": "CSF",
    "Method": "aCompCor",
    "Retained": true,
    "SingularValue": 22.4542741468,
    "VarianceExplained": 0.0161849778
  },
  "dropped_0": {
    "CumulativeVarianceExplained": 0.2241600851,
    "Mask": "Edge",
    "Method": "EdgeRegressor",
    "Retained": false,
    "SingularValue": 120.3266053656,
    "VarianceExplained": 0.0067015721
  },
  "dropped_1": {
    "CumulativeVarianceExplained": 0.2308219919,
    "Mask": "Edge",
    "Method": "EdgeRegressor",
    "Retained": false,
    "SingularValue": 119.9699809613,
    "VarianceExplained": 0.0066619067
  },
  "dropped_10": {
    "CumulativeVarianceExplained": 0.2890606821,
    "Mask": "Edge",
    "Method": "EdgeRegressor",
    "Retained": false,
    "SingularValue": 117.0051621333,
    "VarianceExplained": 0.0063367039
  },
  "dropped_100": {
    "CumulativeVarianceExplained": 0.7876531997,
    "Mask": "Edge",
    "Method": "EdgeRegressor",
    "Retained": false,
    "SingularValue": 102.9487847821,
    "VarianceExplained": 0.0049056416
  },
  "dropped_101": {
    "CumulativeVarianceExplained": 0.792546553,
    "Mask": "Edge",
    "Method": "EdgeRegressor",
    "Retained": false,
    "SingularValue": 102.8197639582,
    "VarianceExplained": 0.0048933533
  },
  "dropped_102": {
    "CumulativeVarianceExplained": 0.7974320848,
    "Mask": "Edge",
    "Method": "EdgeRegressor",
    "Retained": false,
    "SingularValue": 102.7375580226,
    "VarianceExplained": 0.0048855318
  },
  "dropped_103": {
    "CumulativeVarianceExplained": 0.8023058625,
    "Mask": "Edge",
    "Method": "EdgeRegressor",
    "Retained": false,
    "SingularValue": 102.613895072,
    "VarianceExplained": 0.0048737777
  },
  "dropped_104": {
    "CumulativeVarianceExplained": 0.8071643632,
    "Mask": "Edge",
    "Method": "EdgeRegressor",
    "Retained": false,
    "SingularValue": 102.4529463574,
    "VarianceExplained": 0.0048585007
  },
  "dropped_105": {
    "CumulativeVarianceExplained": 0.8120188242,
    "Mask": "Edge",
    "Method": "EdgeRegressor",
    "Retained": false,
    "SingularValue": 102.4103439038,
    "VarianceExplained": 0.004854461
  },
  "dropped_106": {
    "CumulativeVarianceExplained": 0.8168634384,
    "Mask": "Edge",
    "Method": "EdgeRegressor",
    "Retained": false,
    "SingularValue": 102.3064261483,
    "VarianceExplained": 0.0048446142
  },
  "dropped_107": {
    "CumulativeVarianceExplained": 0.8216885773,
    "Mask": "Edge",
    "Method": "EdgeRegressor",
    "Retained": false,
    "SingularValue": 102.1005837885,
    "VarianceExplained": 0.0048251389
  },
  "dropped_108": {
    "CumulativeVarianceExplained": 0.8264825433,
    "Mask": "Edge",
    "Method": "EdgeRegressor",
    "Retained": false,
    "SingularValue": 101.7702378655,
    "VarianceExplained": 0.004793966
  },
  "dropped_109": {
    "CumulativeVarianceExplained": 0.8312636401,
    "Mask": "Edge",
    "Method": "EdgeRegressor",
    "Retained": false,
    "SingularValue": 101.6335477875,
    "VarianceExplained": 0.0047810968
  },
  "dropped_11": {
    "CumulativeVarianceExplained": 0.2953549065,
    "Mask": "Edge",
    "Method": "EdgeRegressor",
    "Retained": false,
    "SingularValue": 116.6123171893,
    "VarianceExplained": 0.0062942243
  },
  "dropped_110": {
    "CumulativeVarianceExplained": 0.8360298311,
    "Mask": "Edge",
    "Method": "EdgeRegressor",
    "Retained": false,
    "SingularValue": 101.4749949253,
    "VarianceExplained": 0.004766191
  },
  "dropped_111": {
    "CumulativeVarianceExplained": 0.8407921026,
    "Mask": "Edge",
    "Method": "EdgeRegressor",
    "Retained": false,
    "SingularValue": 101.4332613323,
    "VarianceExplained": 0.0047622715
  },
  "dropped_112": {
    "CumulativeVarianceExplained": 0.8455436245,
    "Mask": "Edge",
    "Method": "EdgeRegressor",
    "Retained": false,
    "SingularValue": 101.3187178296,
    "VarianceExplained": 0.0047515219
  },
  "dropped_113": {
    "CumulativeVarianceExplained": 0.8502826143,
    "Mask": "Edge",
    "Method": "EdgeRegressor",
    "Retained": false,
    "SingularValue": 101.1850155296,
    "VarianceExplained": 0.0047389898
  },
  "dropped_114": {
    "CumulativeVarianceExplained": 0.8550160209,
    "Mask": "Edge",
    "Method": "EdgeRegressor",
    "Retained": false,
    "SingularValue": 101.1253933667,
    "VarianceExplained": 0.0047334066
  },
  "dropped_115": {
    "CumulativeVarianceExplained": 0.8597373355,
    "Mask": "Edge",
    "Method": "EdgeRegressor",
    "Retained": false,
    "SingularValue": 100.9961424232,
    "VarianceExplained": 0.0047213146
  },
  "dropped_116": {
    "CumulativeVarianceExplained": 0.8644364524,
    "Mask": "Edge",
    "Method": "EdgeRegressor",
    "Retained": false,
    "SingularValue": 100.7584411865,
    "VarianceExplained": 0.0046991169
  },
  "dropped_117": {
    "CumulativeVarianceExplained": 0.8691219032,
    "Mask": "Edge",
    "Method": "EdgeRegressor",
    "Retained": false,
    "SingularValue": 100.6118203408,
    "VarianceExplained": 0.0046854508
  },
  "dropped_118": {
    "CumulativeVarianceExplained": 0.8737943505,
    "Mask": "Edge",
    "Method": "EdgeRegressor",
    "Retained": false,
    "SingularValue": 100.4721099155,
    "VarianceExplained": 0.0046724473
  },
  "dropped_119": {
    "CumulativeVarianceExplained": 0.8784473649,
    "Mask": "Edge",
    "Method": "EdgeRegressor",
    "Retained": false,
    "SingularValue": 100.2629576409,
    "VarianceExplained": 0.0046530143
  },
  "dropped_12": {
    "CumulativeVarianceExplained": 0.3016226521,
    "Mask": "Edge",
    "Method": "EdgeRegressor",
    "Retained": false,
    "SingularValue": 116.3667750197,
    "VarianceExplained": 0.0062677457
  },
  "dropped_120": {
    "CumulativeVarianceExplained": 0.8830762892,
    "Mask": "Edge",
    "Method": "EdgeRegressor",
    "Retained": false,
    "SingularValue": 100.0030756812,
    "VarianceExplained": 0.0046289243
  },
  "dropped_121": {
    "CumulativeVarianceExplained": 0.887698097,
    "Mask": "Edge",
    "Method": "EdgeRegressor",
    "Retained": false,
    "SingularValue": 99.9261728266,
    "VarianceExplained": 0.0046218078
  },
  "dropped_122": {
    "CumulativeVarianceExplained": 0.892301989,
    "Mask": "Edge",
    "Method": "EdgeRegressor",
    "Retained": false,
    "SingularValue": 99.7323102571,
    "VarianceExplained": 0.004603892
  },
  "dropped_123": {
    "CumulativeVarianceExplained": 0.8968889978,
    "Mask": "Edge",
    "Method": "EdgeRegressor",
    "Retained": false,
    "SingularValue": 99.5492754329,
    "VarianceExplained": 0.0045870088
  },
  "dropped_124": {
    "CumulativeVarianceExplained": 0.9014527531,
    "Mask": "Edge",
    "Method": "EdgeRegressor",
    "Retained": false,
    "SingularValue": 99.2966255362,
    "VarianceExplained": 0.0045637553
  },
  "dropped_125": {
    "CumulativeVarianceExplained": 0.9060115759,
    "Mask": "Edge",
    "Method": "EdgeRegressor",
    "Retained": false,
    "SingularValue": 99.2429518639,
    "VarianceExplained": 0.0045588228
  },
  "dropped_126": {
    "CumulativeVarianceExplained": 0.9105495183,
    "Mask": "Edge",
    "Method": "EdgeRegressor",
    "Retained": false,
    "SingularValue": 99.0154134838,
    "VarianceExplained": 0.0045379424
  },
  "dropped_127": {
    "CumulativeVarianceExplained": 0.9150826657,
    "Mask": "Edge",
    "Method": "EdgeRegressor",
    "Retained": false,
    "SingularValue": 98.9630872214,
    "VarianceExplained": 0.0045331474
  },
  "dropped_128": {
    "CumulativeVarianceExplained": 0.9195974041,
    "Mask": "Edge",
    "Method": "EdgeRegressor",
    "Retained": false,
    "SingularValue": 98.761940307,
    "VarianceExplained": 0.0045147384
  },
  "dropped_129": {
    "CumulativeVarianceExplained": 0.9240958614,
    "Mask": "Edge",
    "Method": "EdgeRegressor",
    "Retained": false,
    "SingularValue": 98.5837010629,
    "VarianceExplained": 0.0044984573
  },
  "dropped_13": {
    "CumulativeVarianceExplained": 0.3078524626,
    "Mask": "Edge",
    "Method": "EdgeRegressor",
    "Retained": false,
    "SingularValue": 116.0140893046,
    "VarianceExplained": 0.0062298105
  },
  "dropped_130": {
    "CumulativeVarianceExplained": 0.9285711669,
    "Mask": "Edge",
    "Method": "EdgeRegressor",
    "Retained": false,
    "SingularValue": 98.3296871992,
    "VarianceExplained": 0.0044753055
  },
  "dropped_131": {
    "CumulativeVarianceExplained": 0.9330300226,
    "Mask": "Edge",
    "Method": "EdgeRegressor",
    "Retained": false,
    "SingularValue": 98.1488065637,
    "VarianceExplained": 0.0044588557
  },
  "dropped_132": {
    "CumulativeVarianceExplained": 0.9374690416,
    "Mask": "Edge",
    "Method": "EdgeRegressor",
    "Retained": false,
    "SingularValue": 97.9302397791,
    "VarianceExplained": 0.004439019
  },
  "dropped_133": {
    "CumulativeVarianceExplained": 0.9418851135,
    "Mask": "Edge",
    "Method": "EdgeRegressor",
    "Retained": false,
    "SingularValue": 97.6767911586,
    "VarianceExplained": 0.0044160719
  },
  "dropped_134": {
    "CumulativeVarianceExplained": 0.9462940181,
    "Mask": "Edge",
    "Method": "EdgeRegressor",
    "Retained": false,
    "SingularValue": 97.5974941171,
    "VarianceExplained": 0.0044089046
  },
  "dropped_135": {
    "CumulativeVarianceExplained": 0.9506842243,
    "Mask": "Edge",
    "Method": "EdgeRegressor",
    "Retained": false,
    "SingularValue": 97.3903169774,
    "VarianceExplained": 0.0043902063
  },
  "dropped_136": {
    "CumulativeVarianceExplained": 0.9550542348,
    "Mask": "Edge",
    "Method": "EdgeRegressor",
    "Retained": false,
    "SingularValue": 97.166051582,
    "VarianceExplained": 0.0043700105
  },
  "dropped_137": {
    "CumulativeVarianceExplained": 0.9593902685,
    "Mask": "Edge",
    "Method": "EdgeRegressor",
    "Retained": false,
    "SingularValue": 96.7875816198,
    "VarianceExplained": 0.0043360337
  },
  "dropped_138": {
    "CumulativeVarianceExplained": 0.9637252156,
    "Mask": "Edge",
    "Method": "EdgeRegressor",
    "Retained": false,
    "SingularValue": 96.7754545356,
    "VarianceExplained": 0.0043349472
  },
  "dropped_139": {
    "CumulativeVarianceExplained": 0.9680495117,
    "Mask": "Edge",
    "Method": "EdgeRegressor",
    "Retained": false,
    "SingularValue": 96.6564916395,
    "VarianceExplained": 0.0043242961
  },
  "dropped_14": {
    "CumulativeVarianceExplained": 0.3140632223,
    "Mask": "Edge",
    "Method": "EdgeRegressor",
    "Retained": false,
    "SingularValue": 115.8365670795,
    "VarianceExplained": 0.0062107597
  },
  "dropped_140": {
    "CumulativeVarianceExplained": 0.9723506057,
    "Mask": "Edge",
    "Method": "EdgeRegressor",
    "Retained": false,
    "SingularValue": 96.3968365833,
    "VarianceExplained": 0.004301094
  },
  "dropped_141": {
    "CumulativeVarianceExplained": 0.976614355,
    "Mask": "Edge",
    "Method": "EdgeRegressor",
    "Retained": false,
    "SingularValue": 95.9774367179,
    "VarianceExplained": 0.0042637493
  },
  "dropped_142": {
    "CumulativeVarianceExplained": 0.9808738033,
    "Mask": "Edge",
    "Method": "EdgeRegressor",
    "Retained": false,
    "SingularValue": 95.929016446,
    "VarianceExplained": 0.0042594483
  },
  "dropped_143": {
    "CumulativeVarianceExplained": 0.9851185966,
    "Mask": "Edge",
    "Method": "EdgeRegressor",
    "Retained": false,
    "SingularValue": 95.7638480248,
    "VarianceExplained": 0.0042447933
  },
  "dropped_144": {
    "CumulativeVarianceExplained": 0.9893385554,
    "Mask": "Edge",
    "Method": "EdgeRegressor",
    "Retained": false,
    "SingularValue": 95.4833006454,
    "VarianceExplained": 0.0042199588
  },
  "dropped_145": {
    "CumulativeVarianceExplained": 0.9935091924,
    "Mask": "Edge",
    "Method": "EdgeRegressor",
    "Retained": false,
    "SingularValue": 94.9236680577,
    "VarianceExplained": 0.004170637
  },
  "dropped_146": {
    "CumulativeVarianceExplained": 0.997135888,
    "Mask": "Edge",
    "Method": "EdgeRegressor",
    "Retained": false,
    "SingularValue": 88.5174446384,
    "VarianceExplained": 0.0036266956
  },
  "dropped_147": {
    "CumulativeVarianceExplained": 1.0,
    "Mask": "Edge",
    "Method": "EdgeRegressor",
    "Retained": false,
    "SingularValue": 78.6626028161,
    "VarianceExplained": 0.002864112
  },
  "dropped_148": {
    "CumulativeVarianceExplained": 1.0,
    "Mask": "Edge",
    "Method": "EdgeRegressor",
    "Retained": false,
    "SingularValue": 0.0,
    "VarianceExplained": 0.0
  },
  "dropped_149": {
    "CumulativeVarianceExplained": 1.0,
    "Mask": "Edge",
    "Method": "EdgeRegressor",
    "Retained": false,
    "SingularValue": 0.0,
    "VarianceExplained": 0.0
  },
  "dropped_15": {
    "CumulativeVarianceExplained": 0.3202519948,
    "Mask": "Edge",
    "Method": "EdgeRegressor",
    "Retained": false,
    "SingularValue": 115.6313439648,
    "VarianceExplained": 0.0061887725
  },
  "dropped_150": {
    "CumulativeVarianceExplained": 1.0,
    "Mask": "Edge",
    "Method": "EdgeRegressor",
    "Retained": false,
    "SingularValue": 0.0,
    "VarianceExplained": 0.0
  },
  "dropped_151": {
    "CumulativeVarianceExplained": 1.0,
    "Mask": "Edge",
    "Method": "EdgeRegressor",
    "Retained": false,
    "SingularValue": 0.0,
    "VarianceExplained": 0.0
  },
  "dropped_152": {
    "CumulativeVarianceExplained": 1.0,
    "Mask": "Edge",
    "Method": "EdgeRegressor",
    "Retained": false,
    "SingularValue": 0.0,
    "VarianceExplained": 0.0
  },
  "dropped_16": {
    "CumulativeVarianceExplained": 0.3264255599,
    "Mask": "Edge",
    "Method": "EdgeRegressor",
    "Retained": false,
    "SingularValue": 115.4891895999,
    "VarianceExplained": 0.0061735652
  },
  "dropped_17": {
    "CumulativeVarianceExplained": 0.3325792224,
    "Mask": "Edge",
    "Method": "EdgeRegressor",
    "Retained": false,
    "SingularValue": 115.3028788769,
    "VarianceExplained": 0.0061536624
  },
  "dropped_18": {
    "CumulativeVarianceExplained": 0.3387077024,
    "Mask": "Edge",
    "Method": "EdgeRegressor",
    "Retained": false,
    "SingularValue": 115.0667124587,
    "VarianceExplained": 0.0061284801
  },
  "dropped_19": {
    "CumulativeVarianceExplained": 0.3448148066,
    "Mask": "Edge",
    "Method": "EdgeRegressor",
    "Retained": false,
    "SingularValue": 114.8658626578,
    "VarianceExplained": 0.0061071041
  },
  "dropped_2": {
    "CumulativeVarianceExplained": 0.2374481259,
    "Mask": "Edge",
    "Method": "EdgeRegressor",
    "Retained": false,
    "SingularValue": 119.6474442424,
    "VarianceExplained": 0.0066261341
  },
  "dropped_20": {
    "CumulativeVarianceExplained": 0.3509026102,
    "Mask": "Edge",
    "Method": "EdgeRegressor",
    "Retained": false,
    "SingularValue": 114.6842118992,
    "VarianceExplained": 0.0060878037
  },
  "dropped_21": {
    "CumulativeVarianceExplained": 0.3569818738,
    "Mask": "Edge",
    "Method": "EdgeRegressor",
    "Retained": false,
    "SingularValue": 114.6037426942,
    "VarianceExplained": 0.0060792635
  },
  "dropped_22": {
    "CumulativeVarianceExplained": 0.3630346372,
    "Mask": "Edge",
    "Method": "EdgeRegressor",
    "Retained": false,
    "SingularValue": 114.3536854067,
    "VarianceExplained": 0.0060527634
  },
  "dropped_23": {
    "CumulativeVarianceExplained": 0.3690654548,
    "Mask": "Edge",
    "Method": "EdgeRegressor",
    "Retained": false,
    "SingularValue": 114.1461880061,
    "VarianceExplained": 0.0060308176
  },
  "dropped_24": {
    "CumulativeVarianceExplained": 0.3750891584,
    "Mask": "Edge",
    "Method": "EdgeRegressor",
    "Retained": false,
    "SingularValue": 114.0788443077,
    "VarianceExplained": 0.0060237036
  },
  "dropped_25": {
    "CumulativeVarianceExplained": 0.3810909882,
    "Mask": "Edge",
    "Method": "EdgeRegressor",
    "Retained": false,
    "SingularValue": 113.871529533,
    "VarianceExplained": 0.0060018298
  },
  "dropped_26": {
    "CumulativeVarianceExplained": 0.387077041,
    "Mask": "Edge",
    "Method": "EdgeRegressor",
    "Retained": false,
    "SingularValue": 113.7217644176,
    "VarianceExplained": 0.0059860528
  },
  "dropped_27": {
    "CumulativeVarianceExplained": 0.3930478405,
    "Mask": "Edge",
    "Method": "EdgeRegressor",
    "Retained": false,
    "SingularValue": 113.5767819118,
    "VarianceExplained": 0.0059707995
  },
  "dropped_28": {
    "CumulativeVarianceExplained": 0.3989888612,
    "Mask": "Edge",
    "Method": "EdgeRegressor",
    "Retained": false,
    "SingularValue": 113.2932013657,
    "VarianceExplained": 0.0059410207
  },
  "dropped_29": {
    "CumulativeVarianceExplained": 0.4049105399,
    "Mask": "Edge",
    "Method": "EdgeRegressor",
    "Retained": false,
    "SingularValue": 113.1086279319,
    "VarianceExplained": 0.0059216787
  },
  "dropped_3": {
    "CumulativeVarianceExplained": 0.2440362043,
    "Mask": "Edge",
    "Method": "EdgeRegressor",
    "Retained": false,
    "SingularValue": 119.3033655574,
    "VarianceExplained": 0.0065880784
  },
  "dropped_30": {
    "CumulativeVarianceExplained": 0.4108148959,
    "Mask": "Edge",
    "Method": "EdgeRegressor",
    "Retained": false,
    "SingularValue": 112.9430691764,
    "VarianceExplained": 0.005904356
  },
  "dropped_31": {
    "CumulativeVarianceExplained": 0.4167012235,
    "Mask": "Edge",
    "Method": "EdgeRegressor",
    "Retained": false,
    "SingularValue": 112.7705063393,
    "VarianceExplained": 0.0058863276
  },
  "dropped_32": {
    "CumulativeVarianceExplained": 0.4225730796,
    "Mask": "Edge",
    "Method": "EdgeRegressor",
    "Retained": false,
    "SingularValue": 112.6317984121,
    "VarianceExplained": 0.0058718561
  },
  "dropped_33": {
    "CumulativeVarianceExplained": 0.4284438413,
    "Mask": "Edge",
    "Method": "EdgeRegressor",
    "Retained": false,
    "SingularValue": 112.621300934,
    "VarianceExplained": 0.0058707616
  },
  "dropped_34": {
    "CumulativeVarianceExplained": 0.4342938904,
    "Mask": "Edge",
    "Method": "EdgeRegressor",
    "Retained": false,
    "SingularValue": 112.4224573046,
    "VarianceExplained": 0.0058500492
  },
  "dropped_35": {
    "CumulativeVarianceExplained": 0.4401128862,
    "Mask": "Edge",
    "Method": "EdgeRegressor",
    "Retained": false,
    "SingularValue": 112.123678659,
    "VarianceExplained": 0.0058189958
  },
  "dropped_36": {
    "CumulativeVarianceExplained": 0.4459292006,
    "Mask": "Edge",
    "Method": "EdgeRegressor",
    "Retained": false,
    "SingularValue": 112.0978416246,
    "VarianceExplained": 0.0058163143
  },
  "dropped_37": {
    "CumulativeVarianceExplained": 0.4517253704,
    "Mask": "Edge",
    "Method": "EdgeRegressor",
    "Retained": false,
    "SingularValue": 111.9035505112,
    "VarianceExplained": 0.0057961698
  },
  "dropped_38": {
    "CumulativeVarianceExplained": 0.4575144062,
    "Mask": "Edge",
    "Method": "EdgeRegressor",
    "Retained": false,
    "SingularValue": 111.834663216,
    "VarianceExplained": 0.0057890358
  },
  "dropped_39": {
    "CumulativeVarianceExplained": 0.4632889215,
    "Mask": "Edge",
    "Method": "EdgeRegressor",
    "Retained": false,
    "SingularValue": 111.6943185327,
    "VarianceExplained": 0.0057745153
  },
  "dropped_4": {
    "CumulativeVarianceExplained": 0.2505978985,
    "Mask": "Edge",
    "Method": "EdgeRegressor",
    "Retained": false,
    "SingularValue": 119.0642302936,
    "VarianceExplained": 0.0065616942
  },
  "dropped_40": {
    "CumulativeVarianceExplained": 0.4690466347,
    "Mask": "Edge",
    "Method": "EdgeRegressor",
    "Retained": false,
    "SingularValue": 111.531702148,
    "VarianceExplained": 0.0057577132
  },
  "dropped_41": {
    "CumulativeVarianceExplained": 0.4747870344,
    "Mask": "Edge",
    "Method": "EdgeRegressor",
    "Retained": false,
    "SingularValue": 111.36388731,
    "VarianceExplained": 0.0057403997
  },
  "dropped_42": {
    "CumulativeVarianceExplained": 0.4805212063,
    "Mask": "Edge",
    "Method": "EdgeRegressor",
    "Retained": false,
    "SingularValue": 111.3034617803,
    "VarianceExplained": 0.005734172
  },
  "dropped_43": {
    "CumulativeVarianceExplained": 0.4862397986,
    "Mask": "Edge",
    "Method": "EdgeRegressor",
    "Retained": false,
    "SingularValue": 111.1521540068,
    "VarianceExplained": 0.0057185923
  },
  "dropped_44": {
    "CumulativeVarianceExplained": 0.4919323236,
    "Mask": "Edge",
    "Method": "EdgeRegressor",
    "Retained": false,
    "SingularValue": 110.8985298204,
    "VarianceExplained": 0.005692525
  },
  "dropped_45": {
    "CumulativeVarianceExplained": 0.4976145023,
    "Mask": "Edge",
    "Method": "EdgeRegressor",
    "Retained": false,
    "SingularValue": 110.7977043392,
    "VarianceExplained": 0.0056821788
  },
  "dropped_46": {
    "CumulativeVarianceExplained": 0.503283381,
    "Mask": "Edge",
    "Method": "EdgeRegressor",
    "Retained": false,
    "SingularValue": 110.6679575846,
    "VarianceExplained": 0.0056688786
  },
  "dropped_47": {
    "CumulativeVarianceExplained": 0.5089441291,
    "Mask": "Edge",
    "Method": "EdgeRegressor",
    "Retained": false,
    "SingularValue": 110.5885670797,
    "VarianceExplained": 0.0056607481
  },
  "dropped_48": {
    "CumulativeVarianceExplained": 0.514575596,
    "Mask": "Edge",
    "Method": "EdgeRegressor",
    "Retained": false,
    "SingularValue": 110.3021769329,
    "VarianceExplained": 0.0056314669
  },
  "dropped_49": {
    "CumulativeVarianceExplained": 0.5201874943,
    "Mask": "Edge",
    "Method": "EdgeRegressor",
    "Retained": false,
    "SingularValue": 110.1103675482,
    "VarianceExplained": 0.0056118983
  },
  "dropped_5": {
    "CumulativeVarianceExplained": 0.2570639786,
    "Mask": "Edge",
    "Method": "EdgeRegressor",
    "Retained": false,
    "SingularValue": 118.1935711235,
    "VarianceExplained": 0.0064660801
  },
  "dropped_50": {
    "CumulativeVarianceExplained": 0.5257910702,
    "Mask": "Edge",
    "Method": "EdgeRegressor",
    "Retained": false,
    "SingularValue": 110.0286914043,
    "VarianceExplained": 0.005603576
  },
  "dropped_51": {
    "CumulativeVarianceExplained": 0.5313764299,
    "Mask": "Edge",
    "Method": "EdgeRegressor",
    "Retained": false,
    "SingularValue": 109.8497030775,
    "VarianceExplained": 0.0055853596
  },
  "dropped_52": {
    "CumulativeVarianceExplained": 0.536958452,
    "Mask": "Edge",
    "Method": "EdgeRegressor",
    "Retained": false,
    "SingularValue": 109.8168782592,
    "VarianceExplained": 0.0055820222
  },
  "dropped_53": {
    "CumulativeVarianceExplained": 0.5425212006,
    "Mask": "Edge",
    "Method": "EdgeRegressor",
    "Retained": false,
    "SingularValue": 109.6271262982,
    "VarianceExplained": 0.0055627485
  },
  "dropped_54": {
    "CumulativeVarianceExplained": 0.5480700146,
    "Mask": "Edge",
    "Method": "EdgeRegressor",
    "Retained": false,
    "SingularValue": 109.4897340658,
    "VarianceExplained": 0.005548814
  },
  "dropped_55": {
    "CumulativeVarianceExplained": 0.553608817,
    "Mask": "Edge",
    "Method": "EdgeRegressor",
    "Retained": false,
    "SingularValue": 109.3909138343,
    "VarianceExplained": 0.0055388024
  },
  "dropped_56": {
    "CumulativeVarianceExplained": 0.5591177621,
    "Mask": "Edge",
    "Method": "EdgeRegressor",
    "Retained": false,
    "SingularValue": 109.0956762384,
    "VarianceExplained": 0.0055089451
  },
  "dropped_57": {
    "CumulativeVarianceExplained": 0.5646159041,
    "Mask": "Edge",
    "Method": "EdgeRegressor",
    "Retained": false,
    "SingularValue": 108.9886551507,
    "VarianceExplained": 0.005498142
  },
  "dropped_58": {
    "CumulativeVarianceExplained": 0.5700962513,
    "Mask": "Edge",
    "Method": "EdgeRegressor",
    "Retained": false,
    "SingularValue": 108.8121405222,
    "VarianceExplained": 0.0054803472
  },
  "dropped_59": {
    "CumulativeVarianceExplained": 0.5755542978,
    "Mask": "Edge",
    "Method": "EdgeRegressor",
    "Retained": false,
    "SingularValue": 108.5905245265,
    "VarianceExplained": 0.0054580465
  },
  "dropped_6": {
    "CumulativeVarianceExplained": 0.2635248514,
    "Mask": "Edge",
    "Method": "EdgeRegressor",
    "Retained": false,
    "SingularValue": 118.1459703323,
    "VarianceExplained": 0.0064608729
  },
  "dropped_60": {
    "CumulativeVarianceExplained": 0.5809980075,
    "Mask": "Edge",
    "Method": "EdgeRegressor",
    "Retained": false,
    "SingularValue": 108.447811776,
    "VarianceExplained": 0.0054437097
  },
  "dropped_61": {
    "CumulativeVarianceExplained": 0.5864339821,
    "Mask": "Edge",
    "Method": "EdgeRegressor",
    "Retained": false,
    "SingularValue": 108.3707368132,
    "VarianceExplained": 0.0054359746
  },
  "dropped_62": {
    "CumulativeVarianceExplained": 0.5918474829,
    "Mask": "Edge",
    "Method": "EdgeRegressor",
    "Retained": false,
    "SingularValue": 108.1464872569,
    "VarianceExplained": 0.0054135008
  },
  "dropped_63": {
    "CumulativeVarianceExplained": 0.597252936,
    "Mask": "Edge",
    "Method": "EdgeRegressor",
    "Retained": false,
    "SingularValue": 108.0660728287,
    "VarianceExplained": 0.0054054531
  },
  "dropped_64": {
    "CumulativeVarianceExplained": 0.6026462249,
    "Mask": "Edge",
    "Method": "EdgeRegressor",
    "Retained": false,
    "SingularValue": 107.9444101987,
    "VarianceExplained": 0.0053932889
  },
  "dropped_65": {
    "CumulativeVarianceExplained": 0.6080276678,
    "Mask": "Edge",
    "Method": "EdgeRegressor",
    "Retained": false,
    "SingularValue": 107.8257985702,
    "VarianceExplained": 0.0053814429
  },
  "dropped_66": {
    "CumulativeVarianceExplained": 0.6133898315,
    "Mask": "Edge",
    "Method": "EdgeRegressor",
    "Retained": false,
    "SingularValue": 107.6324807079,
    "VarianceExplained": 0.0053621637
  },
  "dropped_67": {
    "CumulativeVarianceExplained": 0.6187334391,
    "Mask": "Edge",
    "Method": "EdgeRegressor",
    "Retained": false,
    "SingularValue": 107.4460855265,
    "VarianceExplained": 0.0053436077
  },
  "dropped_68": {
    "CumulativeVarianceExplained": 0.6240699565,
    "Mask": "Edge",
    "Method": "EdgeRegressor",
    "Retained": false,
    "SingularValue": 107.3747782923,
    "VarianceExplained": 0.0053365174
  },
  "dropped_69": {
    "CumulativeVarianceExplained": 0.6293907617,
    "Mask": "Edge",
    "Method": "EdgeRegressor",
    "Retained": false,
    "SingularValue": 107.216590661,
    "VarianceExplained": 0.0053208051
  },
  "dropped_7": {
    "CumulativeVarianceExplained": 0.2699540671,
    "Mask": "Edge",
    "Method": "EdgeRegressor",
    "Retained": false,
    "SingularValue": 117.8561672509,
    "VarianceExplained": 0.0064292157
  },
  "dropped_70": {
    "CumulativeVarianceExplained": 0.6347028357,
    "Mask": "Edge",
    "Method": "EdgeRegressor",
    "Retained": false,
    "SingularValue": 107.1285868559,
    "VarianceExplained": 0.005312074
  },
  "dropped_71": {
    "CumulativeVarianceExplained": 0.6399933644,
    "Mask": "Edge",
    "Method": "EdgeRegressor",
    "Retained": false,
    "SingularValue": 106.9111131639,
    "VarianceExplained": 0.0052905287
  },
  "dropped_72": {
    "CumulativeVarianceExplained": 0.6452726675,
    "Mask": "Edge",
    "Method": "EdgeRegressor",
    "Retained": false,
    "SingularValue": 106.7976302708,
    "VarianceExplained": 0.0052793031
  },
  "dropped_73": {
    "CumulativeVarianceExplained": 0.6505431561,
    "Mask": "Edge",
    "Method": "EdgeRegressor",
    "Retained": false,
    "SingularValue": 106.708435956,
    "VarianceExplained": 0.0052704886
  },
  "dropped_74": {
    "CumulativeVarianceExplained": 0.6558024616,
    "Mask": "Edge",
    "Method": "EdgeRegressor",
    "Retained": false,
    "SingularValue": 106.5951675222,
    "VarianceExplained": 0.0052593055
  },
  "dropped_75": {
    "CumulativeVarianceExplained": 0.6610407797,
    "Mask": "Edge",
    "Method": "EdgeRegressor",
    "Retained": false,
    "SingularValue": 106.3822689473,
    "VarianceExplained": 0.0052383181
  },
  "dropped_76": {
    "CumulativeVarianceExplained": 0.6662761665,
    "Mask": "Edge",
    "Method": "EdgeRegressor",
    "Retained": false,
    "SingularValue": 106.3525000976,
    "VarianceExplained": 0.0052353868
  },
  "dropped_77": {
    "CumulativeVarianceExplained": 0.6714849759,
    "Mask": "Edge",
    "Method": "EdgeRegressor",
    "Retained": false,
    "SingularValue": 106.0822074908,
    "VarianceExplained": 0.0052088094
  },
  "dropped_78": {
    "CumulativeVarianceExplained": 0.6766890611,
    "Mask": "Edge",
    "Method": "EdgeRegressor",
    "Retained": false,
    "SingularValue": 106.0340905594,
    "VarianceExplained": 0.0052040852
  },
  "dropped_79": {
    "CumulativeVarianceExplained": 0.6818778946,
    "Mask": "Edge",
    "Method": "EdgeRegressor",
    "Retained": false,
    "SingularValue": 105.8785978089,
    "VarianceExplained": 0.0051888334
  },
  "dropped_8": {
    "CumulativeVarianceExplained": 0.2763623091,
    "Mask": "Edge",
    "Method": "EdgeRegressor",
    "Retained": false,
    "SingularValue": 117.6637719612,
    "VarianceExplained": 0.006408242
  },
  "dropped_80": {
    "CumulativeVarianceExplained": 0.6870506148,
    "Mask": "Edge",
    "Method": "EdgeRegressor",
    "Retained": false,
    "SingularValue": 105.7140746975,
    "VarianceExplained": 0.0051727203
  },
  "dropped_81": {
    "CumulativeVarianceExplained": 0.6922182175,
    "Mask": "Edge",
    "Method": "EdgeRegressor",
    "Retained": false,
    "SingularValue": 105.6617676632,
    "VarianceExplained": 0.0051676026
  },
  "dropped_82": {
    "CumulativeVarianceExplained": 0.6973605436,
    "Mask": "Edge",
    "Method": "EdgeRegressor",
    "Retained": false,
    "SingularValue": 105.4030365991,
    "VarianceExplained": 0.0051423261
  },
  "dropped_83": {
    "CumulativeVarianceExplained": 0.7024968102,
    "Mask": "Edge",
    "Method": "EdgeRegressor",
    "Retained": false,
    "SingularValue": 105.3409174877,
    "VarianceExplained": 0.0051362666
  },
  "dropped_84": {
    "CumulativeVarianceExplained": 0.70760142,
    "Mask": "Edge",
    "Method": "EdgeRegressor",
    "Retained": false,
    "SingularValue": 105.0157863787,
    "VarianceExplained": 0.0051046097
  },
  "dropped_85": {
    "CumulativeVarianceExplained": 0.7127035992,
    "Mask": "Edge",
    "Method": "EdgeRegressor",
    "Retained": false,
    "SingularValue": 104.9907818436,
    "VarianceExplained": 0.0051021792
  },
  "dropped_86": {
    "CumulativeVarianceExplained": 0.7177901372,
    "Mask": "Edge",
    "Method": "EdgeRegressor",
    "Retained": false,
    "SingularValue": 104.8297293096,
    "VarianceExplained": 0.005086538
  },
  "dropped_87": {
    "CumulativeVarianceExplained": 0.7228605637,
    "Mask": "Edge",
    "Method": "EdgeRegressor",
    "Retained": false,
    "SingularValue": 104.6635745613,
    "VarianceExplained": 0.0050704265
  },
  "dropped_88": {
    "CumulativeVarianceExplained": 0.7279144698,
    "Mask": "Edge",
    "Method": "EdgeRegressor",
    "Retained": false,
    "SingularValue": 104.4929278744,
    "VarianceExplained": 0.0050539061
  },
  "dropped_89": {
    "CumulativeVarianceExplained": 0.732960777,
    "Mask": "Edge",
    "Method": "EdgeRegressor",
    "Retained": false,
    "SingularValue": 104.4143429757,
    "VarianceExplained": 0.0050463072
  },
  "dropped_9": {
    "CumulativeVarianceExplained": 0.2827239782,
    "Mask": "Edge",
    "Method": "EdgeRegressor",
    "Retained": false,
    "SingularValue": 117.2354230827,
    "VarianceExplained": 0.0063616691
  },
  "dropped_90": {
    "CumulativeVarianceExplained": 0.7379891088,
    "Mask": "Edge",
    "Method": "EdgeRegressor",
    "Retained": false,
    "SingularValue": 104.228210191,
    "VarianceExplained": 0.0050283318
  },
  "dropped_91": {
    "CumulativeVarianceExplained": 0.7430138583,
    "Mask": "Edge",
    "Method": "EdgeRegressor",
    "Retained": false,
    "SingularValue": 104.191075941,
    "VarianceExplained": 0.0050247495
  },
  "dropped_92": {
    "CumulativeVarianceExplained": 0.7480234086,
    "Mask": "Edge",
    "Method": "EdgeRegressor",
    "Retained": false,
    "SingularValue": 104.0333750539,
    "VarianceExplained": 0.0050095503
  },
  "dropped_93": {
    "CumulativeVarianceExplained": 0.7530280015,
    "Mask": "Edge",
    "Method": "EdgeRegressor",
    "Retained": false,
    "SingularValue": 103.981886807,
    "VarianceExplained": 0.0050045929
  },
  "dropped_94": {
    "CumulativeVarianceExplained": 0.758003339,
    "Mask": "Edge",
    "Method": "EdgeRegressor",
    "Retained": false,
    "SingularValue": 103.6775168525,
    "VarianceExplained": 0.0049753375
  },
  "dropped_95": {
    "CumulativeVarianceExplained": 0.7629706356,
    "Mask": "Edge",
    "Method": "EdgeRegressor",
    "Retained": false,
    "SingularValue": 103.5937045686,
    "VarianceExplained": 0.0049672966
  },
  "dropped_96": {
    "CumulativeVarianceExplained": 0.7679332835,
    "Mask": "Edge",
    "Method": "EdgeRegressor",
    "Retained": false,
    "SingularValue": 103.5452181898,
    "VarianceExplained": 0.0049626479
  },
  "dropped_97": {
    "CumulativeVarianceExplained": 0.7728830692,
    "Mask": "Edge",
    "Method": "EdgeRegressor",
    "Retained": false,
    "SingularValue": 103.4109463605,
    "VarianceExplained": 0.0049497857
  },
  "dropped_98": {
    "CumulativeVarianceExplained": 0.7778190655,
    "Mask": "Edge",
    "Method": "EdgeRegressor",
    "Retained": false,
    "SingularValue": 103.266802022,
    "VarianceExplained": 0.0049359963
  },
  "dropped_99": {
    "CumulativeVarianceExplained": 0.7827475581,
    "Mask": "Edge",
    "Method": "EdgeRegressor",
    "Retained": false,
    "SingularValue": 103.1882794592,
    "VarianceExplained": 0.0049284926
  },
  "edge_comp_00": {
    "CumulativeVarianceExplained": 0.0170750497,
    "Mask": "Edge",
    "Method": "EdgeRegressor",
    "Retained": true,
    "SingularValue": 192.067685825,
    "VarianceExplained": 0.0170750497
  },
  "edge_comp_01": {
    "CumulativeVarianceExplained": 0.0319371152,
    "Mask": "Edge",
    "Method": "EdgeRegressor",
    "Retained": true,
    "SingularValue": 179.1896422285,
    "VarianceExplained": 0.0148620656
  },
  "edge_comp_02": {
    "CumulativeVarianceExplained": 0.0460946447,
    "Mask": "Edge",
    "Method": "EdgeRegressor",
    "Retained": true,
    "SingularValue": 174.8908360982,
    "VarianceExplained": 0.0141575295
  },
  "edge_comp_03": {
    "CumulativeVarianceExplained": 0.0576132864,
    "Mask": "Edge",
    "Method": "EdgeRegressor",
    "Retained": true,
    "SingularValue": 157.751664596,
    "VarianceExplained": 0.0115186417
  },
  "edge_comp_04": {
    "CumulativeVarianceExplained": 0.0676870474,
    "Mask": "Edge",
    "Method": "EdgeRegressor",
    "Retained": true,
    "SingularValue": 147.5261935228,
    "VarianceExplained": 0.010073761
  },
  "edge_comp_05": {
    "CumulativeVarianceExplained": 0.0773471616,
    "Mask": "Edge",
    "Method": "EdgeRegressor",
    "Retained": true,
    "SingularValue": 144.4656000105,
    "VarianceExplained": 0.0096601142
  },
  "edge_comp_06": {
    "CumulativeVarianceExplained": 0.0867864282,
    "Mask": "Edge",
    "Method": "EdgeRegressor",
    "Retained": true,
    "SingularValue": 142.8046804531,
    "VarianceExplained": 0.0094392666
  },
  "edge_comp_07": {
    "CumulativeVarianceExplained": 0.095930107,
    "Mask": "Edge",
    "Method": "EdgeRegressor",
    "Retained": true,
    "SingularValue": 140.5509539073,
    "VarianceExplained": 0.0091436788
  },
  "edge_comp_08": {
    "CumulativeVarianceExplained": 0.1046864747,
    "Mask": "Edge",
    "Method": "EdgeRegressor",
    "Retained": true,
    "SingularValue": 137.5419925665,
    "VarianceExplained": 0.0087563677
  },
  "edge_comp_09": {
    "CumulativeVarianceExplained": 0.1133553396,
    "Mask": "Edge",
    "Method": "EdgeRegressor",
    "Retained": true,
    "SingularValue": 136.8530349118,
    "VarianceExplained": 0.0086688649
  },
  "edge_comp_10": {
    "CumulativeVarianceExplained": 0.1219509244,
    "Mask": "Edge",
    "Method": "EdgeRegressor",
    "Retained": true,
    "SingularValue": 136.2733809595,
    "VarianceExplained": 0.0085955848
  },
  "edge_comp_11": {
    "CumulativeVarianceExplained": 0.1304686415,
    "Mask": "Edge",
    "Method": "EdgeRegressor",
    "Retained": true,
    "SingularValue": 135.6547238092,
    "VarianceExplained": 0.0085177171
  },
  "edge_comp_12": {
    "CumulativeVarianceExplained": 0.1384828994,
    "Mask": "Edge",
    "Method": "EdgeRegressor",
    "Retained": true,
    "SingularValue": 131.5845719114,
    "VarianceExplained": 0.0080142579
  },
  "edge_comp_13": {
    "CumulativeVarianceExplained": 0.1463899868,
    "Mask": "Edge",
    "Method": "EdgeRegressor",
    "Retained": true,
    "SingularValue": 130.7018057126,
    "VarianceExplained": 0.0079070875
  },
  "edge_comp_14": {
    "CumulativeVarianceExplained": 0.1540726043,
    "Mask": "Edge",
    "Method": "EdgeRegressor",
    "Retained": true,
    "SingularValue": 128.83323793,
    "VarianceExplained": 0.0076826175
  },
  "edge_comp_15": {
    "CumulativeVarianceExplained": 0.1614859022,
    "Mask": "Edge",
    "Method": "EdgeRegressor",
    "Retained": true,
    "SingularValue": 126.5549217275,
    "VarianceExplained": 0.0074132978
  },
  "edge_comp_16": {
    "CumulativeVarianceExplained": 0.1688014222,
    "Mask": "Edge",
    "Method": "EdgeRegressor",
    "Retained": true,
    "SingularValue": 125.7175526129,
    "VarianceExplained": 0.00731552
  },
  "edge_comp_17": {
    "CumulativeVarianceExplained": 0.1760587353,
    "Mask": "Edge",
    "Method": "EdgeRegressor",
    "Retained": true,
    "SingularValue": 125.2164098635,
    "VarianceExplained": 0.0072573132
  },
  "edge_comp_18": {
    "CumulativeVarianceExplained": 0.183129073,
    "Mask": "Edge",
    "Method": "EdgeRegressor",
    "Retained": true,
    "SingularValue": 123.5928628041,
    "VarianceExplained": 0.0070703376
  },
  "edge_comp_19": {
    "CumulativeVarianceExplained": 0.1901175143,
    "Mask": "Edge",
    "Method": "EdgeRegressor",
    "Retained": true,
    "SingularValue": 122.8749849076,
    "VarianceExplained": 0.0069884413
  },
  "edge_comp_20": {
    "CumulativeVarianceExplained": 0.1970741911,
    "Mask": "Edge",
    "Method": "EdgeRegressor",
    "Retained": true,
    "SingularValue": 122.5954159411,
    "VarianceExplained": 0.0069566769
  },
  "edge_comp_21": {
    "CumulativeVarianceExplained": 0.2039517642,
    "Mask": "Edge",
    "Method": "EdgeRegressor",
    "Retained": true,
    "SingularValue": 121.8964121901,
    "VarianceExplained": 0.0068775731
  },
  "edge_comp_22": {
    "CumulativeVarianceExplained": 0.2107186471,
    "Mask": "Edge",
    "Method": "EdgeRegressor",
    "Retained": true,
    "SingularValue": 120.9115102816,
    "VarianceExplained": 0.0067668829
  },
  "edge_comp_23": {
    "CumulativeVarianceExplained": 0.217458513,
    "Mask": "Edge",
    "Method": "EdgeRegressor",
    "Retained": true,
    "SingularValue": 120.669897296,
    "VarianceExplained": 0.0067398659
  },
  "framewise_displacement": {
    "Units": "mm"
  },
  "rot_x": {
    "Description": "Rotation about left-right axis. Also known as \"pitch\".",
    "Units": "rad"
  },
  "rot_y": {
    "Description": "Rotation about anterior-posterior axis. Also known as \"roll\".",
    "Units": "rad"
  },
  "rot_z": {
    "Description": "Rotation about superior-inferior axis. Also known as \"yaw\".",
    "Units": "rad"
  },
  "t_comp_cor_00": {
    "CumulativeVarianceExplained": 0.1225514886,
    "Method": "tCompCor",
    "Retained": true,
    "SingularValue": 135.546289576,
    "VarianceExplained": 0.1225514886
  },
  "t_comp_cor_01": {
    "CumulativeVarianceExplained": 0.211696588,
    "Method": "tCompCor",
    "Retained": true,
    "SingularValue": 115.6051217025,
    "VarianceExplained": 0.0891450994
  },
  "t_comp_cor_02": {
    "CumulativeVarianceExplained": 0.281082965,
    "Method": "tCompCor",
    "Retained": true,
    "SingularValue": 101.991843991,
    "VarianceExplained": 0.0693863769
  },
  "t_comp_cor_03": {
    "CumulativeVarianceExplained": 0.3395128998,
    "Method": "tCompCor",
    "Retained": true,
    "SingularValue": 93.5935756499,
    "VarianceExplained": 0.0584299349
  },
  "t_comp_cor_04": {
    "CumulativeVarianceExplained": 0.3918048345,
    "Method": "tCompCor",
    "Retained": true,
    "SingularValue": 88.541259085,
    "VarianceExplained": 0.0522919347
  },
  "t_comp_cor_05": {
    "CumulativeVarianceExplained": 0.4349533779,
    "Method": "tCompCor",
    "Retained": true,
    "SingularValue": 80.42876651,
    "VarianceExplained": 0.0431485434
  },
  "t_comp_cor_06": {
    "CumulativeVarianceExplained": 0.4729437067,
    "Method": "tCompCor",
    "Retained": true,
    "SingularValue": 75.4683516354,
    "VarianceExplained": 0.0379903288
  },
  "t_comp_cor_07": {
    "CumulativeVarianceExplained": 0.503254434,
    "Method": "tCompCor",
    "Retained": true,
    "SingularValue": 67.4103398604,
    "VarianceExplained": 0.0303107273
  },
  "trans_x": {
    "Description": "Translation along left-right axis.",
    "Units": "mm"
  },
  "trans_y": {
    "Description": "Translation along anterior-posterior axis.",
    "Units": "mm"
  },
  "trans_z": {
    "Description": "Translation along superior-inferior axis.",
    "Units": "mm"
  },
  "w_comp_cor_00": {
    "CumulativeVarianceExplained": 0.0129235077,
    "Mask": "WM",
    "Method": "aCompCor",
    "Retained": true,
    "SingularValue": 49.7496999644,
    "VarianceExplained": 0.0129235077
  },
  "w_comp_cor_01": {
    "CumulativeVarianceExplained": 0.0248172302,
    "Mask": "WM",
    "Method": "aCompCor",
    "Retained": true,
    "SingularValue": 47.7264536791,
    "VarianceExplained": 0.0118937226
  },
  "w_comp_cor_02": {
    "CumulativeVarianceExplained": 0.0363317945,
    "Mask": "WM",
    "Method": "aCompCor",
    "Retained": true,
    "SingularValue": 46.959559808,
    "VarianceExplained": 0.0115145642
  },
  "w_comp_cor_03": {
    "CumulativeVarianceExplained": 0.0475520939,
    "Mask": "WM",
    "Method": "aCompCor",
    "Retained": true,
    "SingularValue": 46.3556299876,
    "VarianceExplained": 0.0112202995
  },
  "w_comp_cor_04": {
    "CumulativeVarianceExplained": 0.0585718862,
    "Mask": "WM",
    "Method": "aCompCor",
    "Retained": true,
    "SingularValue": 45.9395743958,
    "VarianceExplained": 0.0110197923
  },
  "w_comp_cor_05": {
    "CumulativeVarianceExplained": 0.0695145891,
    "Mask": "WM",
    "Method": "aCompCor",
    "Retained": true,
    "SingularValue": 45.7786064712,
    "VarianceExplained": 0.0109427029
  },
  "w_comp_cor_06": {
    "CumulativeVarianceExplained": 0.0802680375,
    "Mask": "WM",
    "Method": "aCompCor",
    "Retained": true,
    "SingularValue": 45.381008284,
    "VarianceExplained": 0.0107534484
  },
  "w_comp_cor_07": {
    "CumulativeVarianceExplained": 0.0907762321,
    "Mask": "WM",
    "Method": "aCompCor",
    "Retained": true,
    "SingularValue": 44.8605213479,
    "VarianceExplained": 0.0105081946
  },
  "w_comp_cor_08": {
    "CumulativeVarianceExplained": 0.10119752,
    "Mask": "WM",
    "Method": "aCompCor",
    "Retained": true,
    "SingularValue": 44.6746296562,
    "VarianceExplained": 0.0104212879
  },
  "w_comp_cor_09": {
    "CumulativeVarianceExplained": 0.1114947824,
    "Mask": "WM",
    "Method": "aCompCor",
    "Retained": true,
    "SingularValue": 44.4079937919,
    "VarianceExplained": 0.0102972624
  },
  "w_comp_cor_10": {
    "CumulativeVarianceExplained": 0.1216996891,
    "Mask": "WM",
    "Method": "aCompCor",
    "Retained": true,
    "SingularValue": 44.208398491,
    "VarianceExplained": 0.0102049067
  },
  "w_comp_cor_11": {
    "CumulativeVarianceExplained": 0.1317995836,
    "Mask": "WM",
    "Method": "aCompCor",
    "Retained": true,
    "SingularValue": 43.9803501202,
    "VarianceExplained": 0.0100998945
  },
  "w_comp_cor_12": {
    "CumulativeVarianceExplained": 0.1417395933,
    "Mask": "WM",
    "Method": "aCompCor",
    "Retained": true,
    "SingularValue": 43.6308494053,
    "VarianceExplained": 0.0099400097
  },
  "w_comp_cor_13": {
    "CumulativeVarianceExplained": 0.1516122654,
    "Mask": "WM",
    "Method": "aCompCor",
    "Retained": true,
    "SingularValue": 43.4828117296,
    "VarianceExplained": 0.0098726721
  },
  "w_comp_cor_14": {
    "CumulativeVarianceExplained": 0.1612740153,
    "Mask": "WM",
    "Method": "aCompCor",
    "Retained": true,
    "SingularValue": 43.0158155136,
    "VarianceExplained": 0.00966175
  },
  "w_comp_cor_15": {
    "CumulativeVarianceExplained": 0.1708602516,
    "Mask": "WM",
    "Method": "aCompCor",
    "Retained": true,
    "SingularValue": 42.8473855557,
    "VarianceExplained": 0.0095862362
  },
  "w_comp_cor_16": {
    "CumulativeVarianceExplained": 0.1803799396,
    "Mask": "WM",
    "Method": "aCompCor",
    "Retained": true,
    "SingularValue": 42.6984020262,
    "VarianceExplained": 0.009519688
  },
  "w_comp_cor_17": {
    "CumulativeVarianceExplained": 0.1897567032,
    "Mask": "WM",
    "Method": "aCompCor",
    "Retained": true,
    "SingularValue": 42.3766622921,
    "VarianceExplained": 0.0093767636
  },
  "w_comp_cor_18": {
    "CumulativeVarianceExplained": 0.1990484198,
    "Mask": "WM",
    "Method": "aCompCor",
    "Retained": true,
    "SingularValue": 42.1840468423,
    "VarianceExplained": 0.0092917166
  },
  "w_comp_cor_19": {
    "CumulativeVarianceExplained": 0.2082718376,
    "Mask": "WM",
    "Method": "aCompCor",
    "Retained": true,
    "SingularValue": 42.0287240208,
    "VarianceExplained": 0.0092234178
  },
  "w_comp_cor_20": {
    "CumulativeVarianceExplained": 0.2174405114,
    "Mask": "WM",
    "Method": "aCompCor",
    "Retained": true,
    "SingularValue": 41.9038110001,
    "VarianceExplained": 0.0091686737
  },
  "w_comp_cor_21": {
    "CumulativeVarianceExplained": 0.2265595062,
    "Mask": "WM",
    "Method": "aCompCor",
    "Retained": true,
    "SingularValue": 41.7901326002,
    "VarianceExplained": 0.0091189949
  },
  "w_comp_cor_22": {
    "CumulativeVarianceExplained": 0.2355866946,
    "Mask": "WM",
    "Method": "aCompCor",
    "Retained": true,
    "SingularValue": 41.5792371218,
    "VarianceExplained": 0.0090271884
  },
  "w_comp_cor_23": {
    "CumulativeVarianceExplained": 0.2445068341,
    "Mask": "WM",
    "Method": "aCompCor",
    "Retained": true,
    "SingularValue": 41.3319682657,
    "VarianceExplained": 0.0089201395
  },
  "w_comp_cor_24": {
    "CumulativeVarianceExplained": 0.2532989317,
    "Mask": "WM",
    "Method": "aCompCor",
    "Retained": true,
    "SingularValue": 41.0342511221,
    "VarianceExplained": 0.0087920975
  },
  "w_comp_cor_25": {
    "CumulativeVarianceExplained": 0.262075655,
    "Mask": "WM",
    "Method": "aCompCor",
    "Retained": true,
    "SingularValue": 40.9983584294,
    "VarianceExplained": 0.0087767233
  },
  "w_comp_cor_26": {
    "CumulativeVarianceExplained": 0.2707973579,
    "Mask": "WM",
    "Method": "aCompCor",
    "Retained": true,
    "SingularValue": 40.8696490443,
    "VarianceExplained": 0.0087217029
  },
  "w_comp_cor_27": {
    "CumulativeVarianceExplained": 0.2794363115,
    "Mask": "WM",
    "Method": "aCompCor",
    "Retained": true,
    "SingularValue": 40.6753065042,
    "VarianceExplained": 0.0086389536
  },
  "w_comp_cor_28": {
    "CumulativeVarianceExplained": 0.2879338758,
    "Mask": "WM",
    "Method": "aCompCor",
    "Retained": true,
    "SingularValue": 40.3410772901,
    "VarianceExplained": 0.0084975642
  },
  "w_comp_cor_29": {
    "CumulativeVarianceExplained": 0.2964159901,
    "Mask": "WM",
    "Method": "aCompCor",
    "Retained": true,
    "SingularValue": 40.3043874247,
    "VarianceExplained": 0.0084821143
  },
  "w_comp_cor_30": {
    "CumulativeVarianceExplained": 0.3047878693,
    "Mask": "WM",
    "Method": "aCompCor",
    "Retained": true,
    "SingularValue": 40.0416292008,
    "VarianceExplained": 0.0083718792
  },
  "w_comp_cor_31": {
    "CumulativeVarianceExplained": 0.3131036649,
    "Mask": "WM",
    "Method": "aCompCor",
    "Retained": true,
    "SingularValue": 39.9072836861,
    "VarianceExplained": 0.0083157957
  },
  "w_comp_cor_32": {
    "CumulativeVarianceExplained": 0.3213370961,
    "Mask": "WM",
    "Method": "aCompCor",
    "Retained": true,
    "SingularValue": 39.7091592158,
    "VarianceExplained": 0.0082334311
  },
  "w_comp_cor_33": {
    "CumulativeVarianceExplained": 0.3295167097,
    "Mask": "WM",
    "Method": "aCompCor",
    "Retained": true,
    "SingularValue": 39.5791677301,
    "VarianceExplained": 0.0081796136
  },
  "w_comp_cor_34": {
    "CumulativeVarianceExplained": 0.3375768794,
    "Mask": "WM",
    "Method": "aCompCor",
    "Retained": true,
    "SingularValue": 39.2891251572,
    "VarianceExplained": 0.0080601698
  },
  "w_comp_cor_35": {
    "CumulativeVarianceExplained": 0.3456085899,
    "Mask": "WM",
    "Method": "aCompCor",
    "Retained": true,
    "SingularValue": 39.2197017777,
    "VarianceExplained": 0.0080317105
  },
  "w_comp_cor_36": {
    "CumulativeVarianceExplained": 0.3535871373,
    "Mask": "WM",
    "Method": "aCompCor",
    "Retained": true,
    "SingularValue": 39.0896855524,
    "VarianceExplained": 0.0079785473
  },
  "w_comp_cor_37": {
    "CumulativeVarianceExplained": 0.3615248229,
    "Mask": "WM",
    "Method": "aCompCor",
    "Retained": true,
    "SingularValue": 38.9894591721,
    "VarianceExplained": 0.0079376856
  },
  "w_comp_cor_38": {
    "CumulativeVarianceExplained": 0.3693561384,
    "Mask": "WM",
    "Method": "aCompCor",
    "Retained": true,
    "SingularValue": 38.727335932,
    "VarianceExplained": 0.0078313155
  },
  "w_comp_cor_39": {
    "CumulativeVarianceExplained": 0.3771569089,
    "Mask": "WM",
    "Method": "aCompCor",
    "Retained": true,
    "SingularValue": 38.6517369968,
    "VarianceExplained": 0.0078007706
  },
  "w_comp_cor_40": {
    "CumulativeVarianceExplained": 0.3848136682,
    "Mask": "WM",
    "Method": "aCompCor",
    "Retained": true,
    "SingularValue": 38.2932970228,
    "VarianceExplained": 0.0076567593
  },
  "w_comp_cor_41": {
    "CumulativeVarianceExplained": 0.3924149745,
    "Mask": "WM",
    "Method": "aCompCor",
    "Retained": true,
    "SingularValue": 38.1543781862,
    "VarianceExplained": 0.0076013063
  },
  "w_comp_cor_42": {
    "CumulativeVarianceExplained": 0.4000008227,
    "Mask": "WM",
    "Method": "aCompCor",
    "Retained": true,
    "SingularValue": 38.1155628077,
    "VarianceExplained": 0.0075858482
  },
  "w_comp_cor_43": {
    "CumulativeVarianceExplained": 0.4074782604,
    "Mask": "WM",
    "Method": "aCompCor",
    "Retained": true,
    "SingularValue": 37.8422252494,
    "VarianceExplained": 0.0074774377
  },
  "w_comp_cor_44": {
    "CumulativeVarianceExplained": 0.4148953498,
    "Mask": "WM",
    "Method": "aCompCor",
    "Retained": true,
    "SingularValue": 37.6892085485,
    "VarianceExplained": 0.0074170893
  },
  "w_comp_cor_45": {
    "CumulativeVarianceExplained": 0.4222684066,
    "Mask": "WM",
    "Method": "aCompCor",
    "Retained": true,
    "SingularValue": 37.5771687555,
    "VarianceExplained": 0.0073730569
  },
  "w_comp_cor_46": {
    "CumulativeVarianceExplained": 0.4295861894,
    "Mask": "WM",
    "Method": "aCompCor",
    "Retained": true,
    "SingularValue": 37.4360502733,
    "VarianceExplained": 0.0073177828
  },
  "w_comp_cor_47": {
    "CumulativeVarianceExplained": 0.4368492463,
    "Mask": "WM",
    "Method": "aCompCor",
    "Retained": true,
    "SingularValue": 37.2958049492,
    "VarianceExplained": 0.0072630568
  },
  "w_comp_cor_48": {
    "CumulativeVarianceExplained": 0.4440622043,
    "Mask": "WM",
    "Method": "aCompCor",
    "Retained": true,
    "SingularValue": 37.1669536516,
    "VarianceExplained": 0.007212958
  },
  "w_comp_cor_49": {
    "CumulativeVarianceExplained": 0.4512433329,
    "Mask": "WM",
    "Method": "aCompCor",
    "Retained": true,
    "SingularValue": 37.0848574698,
    "VarianceExplained": 0.0071811286
  },
  "w_comp_cor_50": {
    "CumulativeVarianceExplained": 0.4583884309,
    "Mask": "WM",
    "Method": "aCompCor",
    "Retained": true,
    "SingularValue": 36.9917058839,
    "VarianceExplained": 0.007145098
  },
  "w_comp_cor_51": {
    "CumulativeVarianceExplained": 0.4654574433,
    "Mask": "WM",
    "Method": "aCompCor",
    "Retained": true,
    "SingularValue": 36.7942228963,
    "VarianceExplained": 0.0070690124
  },
  "w_comp_cor_52": {
    "CumulativeVarianceExplained": 0.4724525959,
    "Mask": "WM",
    "Method": "aCompCor",
    "Retained": true,
    "SingularValue": 36.6014981329,
    "VarianceExplained": 0.0069951527
  },
  "w_comp_cor_53": {
    "CumulativeVarianceExplained": 0.4794107208,
    "Mask": "WM",
    "Method": "aCompCor",
    "Retained": true,
    "SingularValue": 36.5044972837,
    "VarianceExplained": 0.0069581248
  },
  "w_comp_cor_54": {
    "CumulativeVarianceExplained": 0.4863192532,
    "Mask": "WM",
    "Method": "aCompCor",
    "Retained": true,
    "SingularValue": 36.3741760654,
    "VarianceExplained": 0.0069085325
  },
  "w_comp_cor_55": {
    "CumulativeVarianceExplained": 0.4931685817,
    "Mask": "WM",
    "Method": "aCompCor",
    "Retained": true,
    "SingularValue": 36.2179829027,
    "VarianceExplained": 0.0068493284
  },
  "w_comp_cor_56": {
    "CumulativeVarianceExplained": 0.4999776944,
    "Mask": "WM",
    "Method": "aCompCor",
    "Retained": true,
    "SingularValue": 36.1114996938,
    "VarianceExplained": 0.0068091127
  },
  "w_comp_cor_57": {
    "CumulativeVarianceExplained": 0.5067315525,
    "Mask": "WM",
    "Method": "aCompCor",
    "Retained": true,
    "SingularValue": 35.9646823689,
    "VarianceExplained": 0.0067538581
  }
}